awesome_py_utils/__init__.py
awesome_py_utils/example.py
awesome_py_utils-0.0.1.dist-info/LICENSE
awesome_py_utils-0.0.1.dist-info/METADATA
awesome_py_utils-0.0.1.dist-info/WHEEL
awesome_py_utils-0.0.1.dist-info/top_level.txt
awesome_py_utils-0.0.1.dist-info/RECORD
