Metadata-Version: 2.1
Name: awesome-py-utils
Version: 0.0.1
Summary: Collection of Awesome Python Utilities
Author-email: Manikanth Reddy <manikanth.iitkgp@gmail.com>
Project-URL: Homepage, https://github.com/manikanthr5/awesome_py_utils
Project-URL: Bug Tracker, https://github.com/manikanthr5/awesome_py_utils/issues
Classifier: Programming Language :: Python :: 3
Classifier: License :: OSI Approved :: MIT License
Classifier: Operating System :: OS Independent
Requires-Python: >=3.7
License-File: LICENSE
